lupupy/__init__.py
lupupy/__main__.py
lupupy/constants.py
lupupy/exceptions.py
lupupy/devices/__init__.py
lupupy/devices/alarm.py
lupupy/devices/binary_sensor.py
lupupy/devices/switch.py
lupupy-0.3.2.dist-info/LICENSE
lupupy-0.3.2.dist-info/METADATA
lupupy-0.3.2.dist-info/WHEEL
lupupy-0.3.2.dist-info/entry_points.txt
lupupy-0.3.2.dist-info/top_level.txt
lupupy-0.3.2.dist-info/RECORD
